ChainTranslator/__init__.py
ChainTranslator/__main__.py
ChainTranslator-1.0.7.dist-info/LICENSE
ChainTranslator-1.0.7.dist-info/METADATA
ChainTranslator-1.0.7.dist-info/WHEEL
ChainTranslator-1.0.7.dist-info/entry_points.txt
ChainTranslator-1.0.7.dist-info/top_level.txt
ChainTranslator-1.0.7.dist-info/RECORD
